filescli/__init__.py
filescli-0.0.2.dist-info/METADATA
filescli-0.0.2.dist-info/WHEEL
filescli-0.0.2.dist-info/entry_points.txt
filescli-0.0.2.dist-info/licenses/LICENSE
filescli-0.0.2.dist-info/RECORD
