Metadata-Version: 2.1
Name: filescli
Version: 0.0.2
Summary: File manager for the command line
Project-URL: Homepage, https://github.com/lestec-al/files
Project-URL: Bug Tracker, https://github.com/lestec-al/files/issues
Author-email: Alex Yurhel <alexyurgel@gmail.com>
License-File: LICENSE
Classifier: License :: OSI Approved :: MIT License
Classifier: Operating System :: OS Independent
Classifier: Programming Language :: Python :: 3
Requires-Python: >=3.8
